Metadata-Version: 2.1
Name: prophyle
Version: 0.3.3.2
Summary: ProPhyle metagenomic classifier
Home-page: https://github.com/prophyle/prophyle
Download-URL: https://github.com/prophyle/prophyle/releases
Author: Karel Brinda, Kamil Salikhov, Simone Pignotti, Gregory Kucherov
Author-email: kbrinda@hsph.harvard.edu, salikhov.kamil@gmail.com, pignottisimone@gmail.com, gregory.kucherov@univ-mlv.fr
License: MIT
Keywords: metagenomics classification NGS
Classifier: Development Status :: 5 - Production/Stable
Classifier: Programming Language :: Python :: 3 :: Only
Classifier: Operating System :: Unix
Classifier: Environment :: Console
Classifier: License :: OSI Approved :: MIT License
Classifier: Intended Audience :: Science/Research
Classifier: Topic :: Scientific/Engineering :: Bio-Informatics
License-File: LICENSE.txt
Requires-Dist: ete3
Requires-Dist: wheel
Requires-Dist: bitarray
Requires-Dist: psutil
Requires-Dist: pysam
Requires-Dist: scipy
Requires-Dist: six
